trace_mcp/main.py
trace_mcp/bin/arm64-v8a/traceserver
trace_mcp/bin/armeabi-v7a/traceserver
trace_mcp/bin/x86/traceserver
trace_mcp/bin/x86_64/traceserver
trace_mcp-1.0.1.dist-info/METADATA
trace_mcp-1.0.1.dist-info/WHEEL
trace_mcp-1.0.1.dist-info/entry_points.txt
trace_mcp-1.0.1.dist-info/top_level.txt
trace_mcp-1.0.1.dist-info/RECORD
