Metadata-Version: 2.4
Name: trace-mcp
Version: 1.0.1
Summary: A Python MCP server for controlling Android system tracing via a native traceserver binary, supporting device selection and custom port forwarding. Designed for use with the uv/uvx toolchain.
Requires-Python: >=3.12
Requires-Dist: mcp>=1.8.0
